Workbook

Sheet Cover
B3: DCF Model- Individual Assignment
B8: Submitted to - Prof. Pulin Aggarwal
B10: Submitted by - Omjee(25PGDM034)
B13: Video Link -
B15: https://drive.google.com/file/d/1k_QBqPZNkdEYOCHSCVSIDzXzKsG8dEGS/view?usp=sharing

Sheet Assumptions
A1: VoltDrive Motors — Assumptions
B4: Value | C4: FY2026E | D4: FY2027E | E4: FY2028E | F4: FY2029E | G4: FY2030E
A6: Cost of Capital & Valuation Assumptions
A7: Risk-Free Rate (Rf) | B7: 0.0425
A8: Levered Beta | B8: 1.85
A9: Equity Market Risk Premium (Rm – Rf) | B9: 0.055
A10: Pre-tax Cost of Debt (Kd) | B10: 0.075
A11: Marginal Tax Rate (t) | B11: 0.21
A12: Diluted Shares Outstanding (mm) | B12: 400
A13: Reference Share Price ($) | B13: 8.9
A14: Terminal Growth Rate (g) | B14: 0.025
A16: Volume & Pricing Drivers
A17: Unit Growth % (Vehicles Sold) | C17: 0.12 | D17: 0.25 | E17: 0.35 | F17: 0.28 | G17: 0.18
A18: ASP Anchor ($'000/unit) — FY2027E & FY2030E given; FY26E/28E/29E interpolated straight-line | D18: 68 | G18: 55
A19: Other Revenue (% of Vehicle Sales Revenue) | B19: 0.02
A21: Unit Cost Drivers
A22: Battery Cost per Unit ($'000) | B22: 21 | C22: 18.5 | D22: 15.8 | E22: 13.2 | F22: 11.5 | G22: 10.2
A23: Other Materials/Assembly Cost per Unit ($'000) | B23: 45 | C23: 42 | D23: 38.5 | E23: 34 | F23: 30.5 | G23: 28
A25: Operating Expense Ratios (% of Revenue)
A26: R&D as % of Revenue | C26: 0.14 | D26: 0.115 | E26: 0.09 | F26: 0.075 | G26: 0.065
A27: SG&A as % of Revenue | C27: 0.15 | D27: 0.125 | E27: 0.105 | F27: 0.09 | G27: 0.08
A29: Capacity & Capex Assumptions
A30: FY2025A Installed Capacity, Beginning (units, '000) | B30: 100
A31: Utilization Target % (anchors FY26E & FY30E; FY27E-29E interpolated) | C31: 0.65 | G31: 0.9
A32: Capex per Unit of New Capacity ($mm per '000 units) | B32: 12
A33: Maintenance Capex (% of Revenue) (anchors FY26E & FY30E; interpolated) | C33: 0.035 | G33: 0.025
A35: Debt & Financing Assumptions
A36: ST Debt Draws ($mm) | B36: 0
A37: ST Debt Repayments ($mm) | B37: 0
A38: New LT Debt (% of Total Capex) | B38: 0.5
A39: Scheduled LT Repayment (% of Beginning LT Balance) | B39: 0.05
A40: Minimum Cash Balance ($mm) | B40: 400

Sheet Income Statement
A1: VoltDrive Motors — EV Automobile Manufacturer
A2: Income Statement ($ in millions)
B4: FY2024A | C4: FY2025A | D4: FY2026E | E4: FY2027E | F4: FY2028E | G4: FY2029E | H4: FY2030E
A6: Revenue | B6: 3000 | C6: 4500 | D6: ='Revenue & Cost Drivers'!C13 -> 4835.6757 | E6: ='Revenue & Cost Drivers'!D13 -> 5789.1892 | F6: ='Revenue & Cost Drivers'!E13 -> 7317.3649 | G6: ='Revenue & Cost Drivers'!F13 -> 8728.7351 | H6: ='Revenue & Cost Drivers'!G13 -> 9547.667
A7: Revenue Growth % | C7: =(C6-B6)/B6 -> 0.5 | D7: =(D6-C6)/C6 -> 0.074594595 | E7: =(E6-D6)/D6 -> 0.1971831 | F7: =(F6-E6)/E6 -> 0.26397059 | G7: =(G6-F6)/F6 -> 0.19287958 | H7: =(H6-G6)/G6 -> 0.093820225
A8: Cost of Goods Sold | B8: 2400 | C8: 3375 | D8: ='Revenue & Cost Drivers'!C19 -> 4039.7456 | E8: ='Revenue & Cost Drivers'!D19 -> 4532.194 | F8: ='Revenue & Cost Drivers'!E19 -> 5318.442 | G8: ='Revenue & Cost Drivers'!F19 -> 6057.6153 | H8: ='Revenue & Cost Drivers'!G19 -> 6501.2635
A9: Gross Profit | B9: =B6-B8 -> 600 | C9: =C6-C8 -> 1125 | D9: =D6-D8 -> 795.93005 | E9: =E6-E8 -> 1256.9952 | F9: =F6-F8 -> 1998.9229 | G9: =G6-G8 -> 2671.1199 | H9: =H6-H8 -> 3046.4036
A10: R&D Expense | B10: 300 | C10: 360 | D10: ='Revenue & Cost Drivers'!C22 -> 676.99459 | E10: ='Revenue & Cost Drivers'!D22 -> 665.75676 | F10: ='Revenue & Cost Drivers'!E22 -> 658.56284 | G10: ='Revenue & Cost Drivers'!F22 -> 654.65514 | H10: ='Revenue & Cost Drivers'!G22 -> 620.59836
A11: SG&A Expense | B11: 360 | C11: 450 | D11: ='Revenue & Cost Drivers'!C24 -> 725.35135 | E11: ='Revenue & Cost Drivers'!D24 -> 723.64865 | F11: ='Revenue & Cost Drivers'!E24 -> 768.32331 | G11: ='Revenue & Cost Drivers'!F24 -> 785.58616 | H11: ='Revenue & Cost Drivers'!G24 -> 763.81336
A12: EBITDA | B12: =B9-B10-B11 -> -60 | C12: =C9-C10-C11 -> 315 | D12: =D9-D10-D11 -> -606.4159 | E12: =E9-E10-E11 -> -132.41017 | F12: =F9-F10-F11 -> 572.03674 | G12: =G9-G10-G11 -> 1230.8786 | H12: =H9-H10-H11 -> 1661.9918
A13: Depreciation & Amortization | B13: 150 | C13: 200 | D13: ='Capacity Expansion'!C26 -> 227.42857 | E13: ='Capacity Expansion'!D26 -> 225.48922 | F13: ='Capacity Expansion'!E26 -> 235.82626 | G13: ='Capacity Expansion'!F26 -> 260.40983 | H13: ='Capacity Expansion'!G26 -> 283.38045
A14: EBIT | B14: =B12-B13 -> -210 | C14: =C12-C13 -> 115 | D14: =D12-D13 -> -833.84447 | E14: =E12-E13 -> -357.8994 | F14: =F12-F13 -> 336.21049 | G14: =G12-G13 -> 970.46874 | H14: =H12-H13 -> 1378.6114
A15: Interest Expense | B15: 75 | C15: 85 | D15: ='Debt Schedule'!C24 -> 155.25 | E15: ='Debt Schedule'!D24 -> 155.77405 | F15: ='Debt Schedule'!E24 -> 162.24145 | G15: ='Debt Schedule'!F24 -> 175.78509 | H15: ='Debt Schedule'!G24 -> 188.77956
A16: EBT (Pre-tax Income) | B16: =B14-B15 -> -285 | C16: =C14-C15 -> 30 | D16: =D14-D15 -> -989.09447 | E16: =E14-E15 -> -513.67344 | F16: =F14-F15 -> 173.96904 | G16: =G14-G15 -> 794.68365 | H16: =H14-H15 -> 1189.8318
A17: Tax Expense | B17: 0 | C17: 7.5 | D17: =IF(D16>0,D16*WACC!$B$12,0) -> 0 | E17: =IF(E16>0,E16*WACC!$B$12,0) -> 0 | F17: =IF(F16>0,F16*WACC!$B$12,0) -> 36.533498 | G17: =IF(G16>0,G16*WACC!$B$12,0) -> 166.88357 | H17: =IF(H16>0,H16*WACC!$B$12,0) -> 249.86469
A18: Net Income | B18: =B16-B17 -> -285 | C18: =C16-C17 -> 22.5 | D18: =D16-D17 -> -989.09447 | E18: =E16-E17 -> -513.67344 | F18: =F16-F17 -> 137.43554 | G18: =G16-G17 -> 627.80008 | H18: =H16-H17 -> 939.96715
A20: Gross Margin % | B20: =B9/B6 -> 0.2 | C20: =C9/C6 -> 0.25 | D20: =D9/D6 -> 0.16459542 | E20: =E9/E6 -> 0.21712803 | F20: =F9/F6 -> 0.27317524 | G20: =G9/G6 -> 0.30601454 | H20: =H9/H6 -> 0.31907308
A21: EBITDA Margin % | B21: =B12/B6 -> -0.02 | C21: =C12/C6 -> 0.07 | D21: =D12/D6 -> -0.12540458 | E21: =E12/E6 -> -0.022871972 | F21: =F12/F6 -> 0.078175239 | G21: =G12/G6 -> 0.14101454 | H21: =H12/H6 -> 0.17407308
A22: Net Margin % | B22: =B18/B6 -> -0.095 | C22: =C18/C6 -> 0.005 | D22: =D18/D6 -> -0.20454111 | E22: =E18/E6 -> -0.088729773 | F22: =F18/F6 -> 0.018782108 | G22: =G18/G6 -> 0.071923374 | H22: =H18/H6 -> 0.09844993

Sheet Balance Sheet
A1: VoltDrive Motors — EV Automobile Manufacturer
A2: Balance Sheet ($ in millions)
B4: FY2024A | C4: FY2025A | D4: FY2026E | E4: FY2027E | F4: FY2028E | G4: FY2029E | H4: FY2030E
A5: Assets
A6: Cash & Equivalents | B6: 375 | C6: 482.5 | D6: ='Cash Flow Statement'!D25 -> 400 | E6: ='Cash Flow Statement'!E25 -> 400 | F6: ='Cash Flow Statement'!F25 -> 400 | G6: ='Cash Flow Statement'!G25 -> 728.8663 | H6: ='Cash Flow Statement'!H25 -> 1515.5569
A7: Accounts Receivable | B7: 300 | C7: 450 | D7: ='Income Statement'!D6*('Balance Sheet'!D29/365) -> 483.56757 | E7: ='Income Statement'!E6*('Balance Sheet'!E29/365) -> 578.91892 | F7: ='Income Statement'!F6*('Balance Sheet'!F29/365) -> 731.73649 | G7: ='Income Statement'!G6*('Balance Sheet'!G29/365) -> 872.87351 | H7: ='Income Statement'!H6*('Balance Sheet'!H29/365) -> 954.7667
A8: Inventory | B8: 450 | C8: 675 | D8: ='Income Statement'!D8*('Balance Sheet'!D30/365) -> 807.94913 | E8: ='Income Statement'!E8*('Balance Sheet'!E30/365) -> 906.43879 | F8: ='Income Statement'!F8*('Balance Sheet'!F30/365) -> 1063.6884 | G8: ='Income Statement'!G8*('Balance Sheet'!G30/365) -> 1211.5231 | H8: ='Income Statement'!H8*('Balance Sheet'!H30/365) -> 1300.2527
A9: Total Current Assets | B9: =SUM(B6:B8) -> 1125 | C9: =SUM(C6:C8) -> 1607.5 | D9: =SUM(D6:D8) -> 1691.5167 | E9: =SUM(E6:E8) -> 1885.3577 | F9: =SUM(F6:F8) -> 2195.4249 | G9: =SUM(G6:G8) -> 2813.2629 | H9: =SUM(H6:H8) -> 3770.5763
A10: Net PP&E (incl. Gigafactory) | B10: 2625 | C10: 2985 | D10: ='Capacity Expansion'!C27 -> 2959.546 | E10: ='Capacity Expansion'!D27 -> 3095.2196 | F10: ='Capacity Expansion'!E27 -> 3417.8791 | G10: ='Capacity Expansion'!F27 -> 3719.3684 | H10: ='Capacity Expansion'!G27 -> 3877.3177
A11: Total Assets | B11: =B9+B10 -> 3750 | C11: =C9+C10 -> 4592.5 | D11: =D9+D10 -> 4651.0627 | E11: =E9+E10 -> 4980.5773 | F11: =F9+F10 -> 5613.3039 | G11: =G9+G10 -> 6532.6313 | H11: =H9+H10 -> 7647.894
A13: Liabilities
A14: Accounts Payable | B14: 360 | C14: 540 | D14: ='Income Statement'!D8*('Balance Sheet'!D31/365) -> 646.3593 | E14: ='Income Statement'!E8*('Balance Sheet'!E31/365) -> 725.15103 | F14: ='Income Statement'!F8*('Balance Sheet'!F31/365) -> 850.95072 | G14: ='Income Statement'!G8*('Balance Sheet'!G31/365) -> 969.21844 | H14: ='Income Statement'!H8*('Balance Sheet'!H31/365) -> 1040.2022
A15: Short-term Debt | B15: 190 | C15: 190 | D15: ='Debt Schedule'!C10 -> 190 | E15: ='Debt Schedule'!D10 -> 190 | F15: ='Debt Schedule'!E10 -> 190 | G15: ='Debt Schedule'!F10 -> 190 | H15: ='Debt Schedule'!G10 -> 190
A16: Total Current Liabilities | B16: =SUM(B14:B15) -> 550 | C16: =SUM(C14:C15) -> 730 | D16: =SUM(D14:D15) -> 836.3593 | E16: =SUM(E14:E15) -> 915.15103 | F16: =SUM(F14:F15) -> 1040.9507 | G16: =SUM(G14:G15) -> 1159.2184 | H16: =SUM(H14:H15) -> 1230.2022
A17: Long-term Debt | B17: 1700 | C17: 1880 | D17: ='Debt Schedule'!C18 -> 1886.9873 | E17: ='Debt Schedule'!D18 -> 1973.2193 | F17: ='Debt Schedule'!E18 -> 2153.8012 | G17: ='Debt Schedule'!F18 -> 2327.0608 | H17: ='Debt Schedule'!G18 -> 2431.3726
A18: Total Liabilities | B18: =B16+B17 -> 2250 | C18: =C16+C17 -> 2610 | D18: =D16+D17 -> 2723.3466 | E18: =E16+E17 -> 2888.3704 | F18: =F16+F17 -> 3194.7519 | G18: =G16+G17 -> 3486.2792 | H18: =H16+H17 -> 3661.5747
A20: Equity
A21: Common Stock & APIC | B21: 1875 | C21: 2335 | D21: =C21+'Cash Flow Statement'!D20 -> 3269.3106 | E21: =D21+'Cash Flow Statement'!E20 -> 3947.4749 | F21: =E21+'Cash Flow Statement'!F20 -> 4136.3844 | G21: =F21+'Cash Flow Statement'!G20 -> 4136.3844 | H21: =G21+'Cash Flow Statement'!H20 -> 4136.3844
A22: Retained Earnings | B22: -375 | C22: -352.5 | D22: =C22+'Income Statement'!D18 -> -1341.5945 | E22: =D22+'Income Statement'!E18 -> -1855.2679 | F22: =E22+'Income Statement'!F18 -> -1717.8324 | G22: =F22+'Income Statement'!G18 -> -1090.0323 | H22: =G22+'Income Statement'!H18 -> -150.06514
A23: Total Equity | B23: =B21+B22 -> 1500 | C23: =C21+C22 -> 1982.5 | D23: =D21+D22 -> 1927.7161 | E23: =E21+E22 -> 2092.207 | F23: =F21+F22 -> 2418.552 | G23: =G21+G22 -> 3046.3521 | H23: =H21+H22 -> 3986.3192
A25: Total Liabilities & Equity | B25: =B18+B23 -> 3750 | C25: =C18+C23 -> 4592.5 | D25: =D18+D23 -> 4651.0627 | E25: =E18+E23 -> 4980.5773 | F25: =F18+F23 -> 5613.3039 | G25: =G18+G23 -> 6532.6313 | H25: =H18+H23 -> 7647.894
A26: Balance Check (should be 0) | B26: =B11-B25 -> 0 | C26: =C11-C25 -> 0
A28: Working Capital Metrics (added)
A29: DSO (days) = AR / Revenue x 365 | B29: =B7/'Income Statement'!B6*365 -> 36.5 | C29: =C7/'Income Statement'!C6*365 -> 36.5 | D29: =C29 -> 36.5 | E29: =D29 -> 36.5 | F29: =E29 -> 36.5 | G29: =F29 -> 36.5 | H29: =G29 -> 36.5
A30: DIO (days) = Inventory / COGS x 365 | B30: =B8/'Income Statement'!B8*365 -> 68.4375 | C30: =C8/'Income Statement'!C8*365 -> 73 | D30: =C30 -> 73 | E30: =D30 -> 73 | F30: =E30 -> 73 | G30: =F30 -> 73 | H30: =G30 -> 73
A31: DPO (days) = AP / COGS x 365 | B31: =B14/'Income Statement'!B8*365 -> 54.75 | C31: =C14/'Income Statement'!C8*365 -> 58.4 | D31: =C31 -> 58.4 | E31: =D31 -> 58.4 | F31: =E31 -> 58.4 | G31: =F31 -> 58.4 | H31: =G31 -> 58.4
A32: Net Working Capital ($mm) = AR + Inventory - AP | B32: =B7+B8-B14 -> 390 | C32: =C7+C8-C14 -> 585 | D32: =D7+D8-D14 -> 645.15739 | E32: =E7+E8-E14 -> 760.20668 | F32: =F7+F8-F14 -> 944.47417 | G32: =G7+G8-G14 -> 1115.1781 | H32: =H7+H8-H14 -> 1214.8172
A33: Increase / (Decrease) in NWC ($mm) | C33: =C32-B32 -> 195 | D33: =D32-C32 -> 60.157393 | E33: =E32-D32 -> 115.04928 | F33: =F32-E32 -> 184.26749 | G33: =G32-F32 -> 170.70396 | H33: =H32-G32 -> 99.639117

Sheet Cash Flow Statement
A1: VoltDrive Motors — EV Automobile Manufacturer
A2: Cash Flow Statement ($ in millions)
B4: FY2024A | C4: FY2025A | D4: FY2026E | E4: FY2027E | F4: FY2028E | G4: FY2029E | H4: FY2030E
A5: Operating Activities
A6: Net Income | B6: ='Income Statement'!B18 -> -285 | C6: ='Income Statement'!C18 -> 22.5 | D6: ='Income Statement'!D18 -> -989.09447 | E6: ='Income Statement'!E18 -> -513.67344 | F6: ='Income Statement'!F18 -> 137.43554 | G6: ='Income Statement'!G18 -> 627.80008 | H6: ='Income Statement'!H18 -> 939.96715
A7: Add: D&A | B7: ='Income Statement'!B13 -> 150 | C7: ='Income Statement'!C13 -> 200 | D7: ='Income Statement'!D13 -> 227.42857 | E7: ='Income Statement'!E13 -> 225.48922 | F7: ='Income Statement'!F13 -> 235.82626 | G7: ='Income Statement'!G13 -> 260.40983 | H7: ='Income Statement'!H13 -> 283.38045
A8: (Incr)/Decr in Accounts Receivable | B8: N/A (base year) | C8: =-('Balance Sheet'!C7-'Balance Sheet'!B7) -> -150 | D8: =-('Balance Sheet'!D7-'Balance Sheet'!C7) -> -33.567568 | E8: =-('Balance Sheet'!E7-'Balance Sheet'!D7) -> -95.351351 | F8: =-('Balance Sheet'!F7-'Balance Sheet'!E7) -> -152.81757 | G8: =-('Balance Sheet'!G7-'Balance Sheet'!F7) -> -141.13703 | H8: =-('Balance Sheet'!H7-'Balance Sheet'!G7) -> -81.893189
A9: (Incr)/Decr in Inventory | B9: N/A (base year) | C9: =-('Balance Sheet'!C8-'Balance Sheet'!B8) -> -225 | D9: =-('Balance Sheet'!D8-'Balance Sheet'!C8) -> -132.94913 | E9: =-('Balance Sheet'!E8-'Balance Sheet'!D8) -> -98.489666 | F9: =-('Balance Sheet'!F8-'Balance Sheet'!E8) -> -157.2496 | G9: =-('Balance Sheet'!G8-'Balance Sheet'!F8) -> -147.83466 | H9: =-('Balance Sheet'!H8-'Balance Sheet'!G8) -> -88.729641
A10: Incr/(Decr) in Accounts Payable | B10: N/A (base year) | C10: ='Balance Sheet'!C14-'Balance Sheet'!B14 -> 180 | D10: ='Balance Sheet'!D14-'Balance Sheet'!C14 -> 106.3593 | E10: ='Balance Sheet'!E14-'Balance Sheet'!D14 -> 78.791733 | F10: ='Balance Sheet'!F14-'Balance Sheet'!E14 -> 125.79968 | G10: ='Balance Sheet'!G14-'Balance Sheet'!F14 -> 118.26773 | H10: ='Balance Sheet'!H14-'Balance Sheet'!G14 -> 70.983713
A11: Net Cash from Operating Activities | B11: =B6+B7 -> -135 | C11: =SUM(C6:C10) -> 27.5 | D11: =SUM(D6:D10) -> -821.82329 | E11: =SUM(E6:E10) -> -403.23351 | F11: =SUM(F6:F10) -> 188.99431 | G11: =SUM(G6:G10) -> 717.50596 | H11: =SUM(H6:H10) -> 1123.7085
A13: Investing Activities
A14: Capital Expenditures | B14: -500 | C14: -560 | D14: =-'Capacity Expansion'!C21 -> -201.97459 | E14: =-'Capacity Expansion'!D21 -> -361.16282 | F14: =-'Capacity Expansion'!E21 -> -558.4857 | G14: =-'Capacity Expansion'!F21 -> -561.8992 | H14: =-'Capacity Expansion'!G21 -> -441.32974
A15: Net Cash from Investing Activities | B15: =B14 -> -500 | C15: =C14 -> -560 | D15: =D14 -> -201.97459 | E15: =E14 -> -361.16282 | F15: =F14 -> -558.4857 | G15: =G14 -> -561.8992 | H15: =H14 -> -441.32974
A17: Financing Activities
A18: Debt Issued | B18: 700 | C18: 280 | D18: ='Debt Schedule'!C8+'Debt Schedule'!C16 -> 100.98729 | E18: ='Debt Schedule'!D8+'Debt Schedule'!D16 -> 180.58141 | F18: ='Debt Schedule'!E8+'Debt Schedule'!E16 -> 279.24285 | G18: ='Debt Schedule'!F8+'Debt Schedule'!F16 -> 280.9496 | H18: ='Debt Schedule'!G8+'Debt Schedule'!G16 -> 220.66487
A19: Debt Repaid | B19: -50 | C19: -100 | D19: ='Debt Schedule'!C9+'Debt Schedule'!C17 -> -94 | E19: ='Debt Schedule'!D9+'Debt Schedule'!D17 -> -94.349365 | F19: ='Debt Schedule'!E9+'Debt Schedule'!E17 -> -98.660967 | G19: ='Debt Schedule'!F9+'Debt Schedule'!F17 -> -107.69006 | H19: ='Debt Schedule'!G9+'Debt Schedule'!G17 -> -116.35304
A20: Equity Issued | B20: 1200 | C20: 460 | D20: =MAX(0,'Debt Schedule'!C32-(D24+D11+D15+D18+D19)) -> 934.31058 | E20: =MAX(0,'Debt Schedule'!D32-(E24+E11+E15+E18+E19)) -> 678.16428 | F20: =MAX(0,'Debt Schedule'!E32-(F24+F11+F15+F18+F19)) -> 188.90951 | G20: =MAX(0,'Debt Schedule'!F32-(G24+G11+G15+G18+G19)) -> 0 | H20: =MAX(0,'Debt Schedule'!G32-(H24+H11+H15+H18+H19)) -> 0
A21: Net Cash from Financing Activities | B21: =SUM(B18:B20) -> 1850 | C21: =SUM(C18:C20) -> 640 | D21: =SUM(D18:D20) -> 941.29788 | E21: =SUM(E18:E20) -> 764.39632 | F21: =SUM(F18:F20) -> 369.49139 | G21: =SUM(G18:G20) -> 173.25954 | H21: =SUM(H18:H20) -> 104.31183
A23: Net Change in Cash | B23: =B11+B15+B21 -> 1215 | C23: =C11+C15+C21 -> 107.5 | D23: =D11+D15+D21 -> -82.5 | E23: =E11+E15+E21 -> 0 | F23: =F11+F15+F21 -> 0 | G23: =G11+G15+G21 -> 328.8663 | H23: =H11+H15+H21 -> 786.69057
A24: Beginning Cash Balance | B24: N/A (base year) | C24: ='Balance Sheet'!B6 -> 375 | D24: =C25 -> 482.5 | E24: =D25 -> 400 | F24: =E25 -> 400 | G24: =F25 -> 400 | H24: =G25 -> 728.8663
A25: Ending Cash Balance | B25: ='Balance Sheet'!B6 -> 375 | C25: =C24+C23 -> 482.5 | D25: =D24+D23 -> 400 | E25: =E24+E23 -> 400 | F25: =F24+F23 -> 400 | G25: =G24+G23 -> 728.8663 | H25: =H24+H23 -> 1515.5569
A26: Check vs. Balance Sheet Cash (should be 0) | C26: =C25-'Balance Sheet'!C6 -> 0

Sheet WACC
A1: VoltDrive Motors — WACC Calculation Template
A2: Fill in the yellow input cells and build the formulas in column B. Column D gives guidance only.
A4: Cost of Equity (CAPM)
A5: Risk-Free Rate (Rf) | B5: =Assumptions!B7 -> 0.0425 | D5: e.g., 10-yr Treasury yield
A6: Levered Beta | B6: =Assumptions!B8 -> 1.85 | D6: From comparable EV OEM public betas
A7: Equity Market Risk Premium (Rm – Rf) | B7: =Assumptions!B9 -> 0.055 | D7: Historical or implied ERP
A8: Cost of Equity (Ke) | B8: =B5+(B6*B7) -> 0.14425 | D8: Ke = Rf + Beta × ERP
A10: Cost of Debt
A11: Pre-tax Cost of Debt (Kd) | B11: =Assumptions!B10 -> 0.075 | D11: Try: Interest Expense / Total Debt from IS & BS tabs
A12: Marginal Tax Rate (t) | B12: =Assumptions!B11 -> 0.21 | D12: Statutory corporate tax rate
A13: After-tax Cost of Debt | B13: =B11*(1-B12) -> 0.05925 | D13: Kd × (1 – t)
A15: Capital Structure (Market Value Weights)
A16: Market Value of Equity (E) | B16: =B27*B28 -> 3560 | D16: Share price × shares outstanding (or latest funding round valuation)
A17: Market Value of Debt (D) | B17: ='Balance Sheet'!C15+'Balance Sheet'!C17 -> 2070 | D17: Use Balance Sheet ST + LT Debt (book value proxy)
A18: Total Capital (E + D) | B18: =B16+B17 -> 5630
A19: Weight of Equity (E / (E+D)) | B19: =B16/B18 -> 0.63232682
A20: Weight of Debt (D / (E+D)) | B20: =B17/B18 -> 0.36767318
A22: WACC | B22: =B19*B8+B20*B13 -> 0.11299778 | D22: WACC = We × Ke + Wd × Kd × (1–t)
A26: Equity Value Reference Inputs (ASSUMED - not given in brief)
A27: Diluted Shares Outstanding (mm) | B27: =Assumptions!B12 -> 400
A28: Reference Share Price ($) - proxy for latest funding round | B28: =Assumptions!B13 -> 8.9

Sheet DCF Valuation
A1: VoltDrive Motors — DCF Valuation Template (Blank — Build the Formulas)
A2: $ in millions. Fill in every white cell below — no formulas are pre-built.
B4: FY2026E | C4: FY2027E | D4: FY2028E | E4: FY2029E | F4: FY2030E | G4: Terminal Year
A6: Revenue | B6: ='Income Statement'!D6 -> 4835.6757 | C6: ='Income Statement'!E6 -> 5789.1892 | D6: ='Income Statement'!F6 -> 7317.3649 | E6: ='Income Statement'!G6 -> 8728.7351 | F6: ='Income Statement'!H6 -> 9547.667 | G6: =F6*(1+$B$25) -> 9786.3587
A7: Revenue Growth % | B7: ='Income Statement'!D7 -> 0.074594595 | C7: ='Income Statement'!E7 -> 0.1971831 | D7: ='Income Statement'!F7 -> 0.26397059 | E7: ='Income Statement'!G7 -> 0.19287958 | F7: ='Income Statement'!H7 -> 0.093820225 | G7: =$B$25 -> 0.025
A8: EBITDA | B8: ='Income Statement'!D12 -> -606.4159 | C8: ='Income Statement'!E12 -> -132.41017 | D8: ='Income Statement'!F12 -> 572.03674 | E8: ='Income Statement'!G12 -> 1230.8786 | F8: ='Income Statement'!H12 -> 1661.9918 | G8: =F8*(1+$B$25) -> 1703.5416
A9: EBITDA Margin % | B9: =B8/B6 -> -0.12540458 | C9: =C8/C6 -> -0.022871972 | D9: =D8/D6 -> 0.078175239 | E9: =E8/E6 -> 0.14101454 | F9: =F8/F6 -> 0.17407308 | G9: =G8/G6 -> 0.17407308
A10: Less: D&A | B10: =-'Income Statement'!D13 -> -227.42857 | C10: =-'Income Statement'!E13 -> -225.48922 | D10: =-'Income Statement'!F13 -> -235.82626 | E10: =-'Income Statement'!G13 -> -260.40983 | F10: =-'Income Statement'!H13 -> -283.38045 | G10: =F10*(1+B25) -> -290.46496
A11: EBIT | B11: =B8+B10 -> -833.84447 | C11: =C8+C10 -> -357.8994 | D11: =D8+D10 -> 336.21049 | E11: =E8+E10 -> 970.46874 | F11: =F8+F10 -> 1378.6114 | G11: =G8+G10 -> 1413.0767
A12: Less: Taxes on EBIT | B12: =-B11*WACC!$B$12 -> 175.10734 | C12: =-C11*WACC!$B$12 -> 75.158873 | D12: =-D11*WACC!$B$12 -> -70.604203 | E12: =-E11*WACC!$B$12 -> -203.79844 | F12: =-F11*WACC!$B$12 -> -289.50839 | G12: =F12*(1+$B$25) -> -296.7461
A13: EBIAT (NOPAT) | B13: =B11+B12 -> -658.73713 | C13: =C11+C12 -> -282.74052 | D13: =D11+D12 -> 265.60629 | E13: =E11+E12 -> 766.67031 | F13: =F11+F12 -> 1089.103 | G13: =G11+G12 -> 1116.3306
A14: Add: D&A | B14: ='Income Statement'!D13 -> 227.42857 | C14: ='Income Statement'!E13 -> 225.48922 | D14: ='Income Statement'!F13 -> 235.82626 | E14: ='Income Statement'!G13 -> 260.40983 | F14: ='Income Statement'!H13 -> 283.38045 | G14: =F14*(1+B25) -> 290.46496
A15: Less: Capital Expenditures | B15: =-'Capacity Expansion'!C21 -> -201.97459 | C15: =-'Capacity Expansion'!D21 -> -361.16282 | D15: =-'Capacity Expansion'!E21 -> -558.4857 | E15: =-'Capacity Expansion'!F21 -> -561.8992 | F15: =-'Capacity Expansion'!G21 -> -441.32974 | G15: =F15*(1+B25) -> -452.36298
A16: Less: Increase in Net Working Capital | B16: =-'Balance Sheet'!D33 -> -60.157393 | C16: =-'Balance Sheet'!E33 -> -115.04928 | D16: =-'Balance Sheet'!F33 -> -184.26749 | E16: =-'Balance Sheet'!G33 -> -170.70396 | F16: =-'Balance Sheet'!H33 -> -99.639117 | G16: =F16*(1+B25) -> -102.1301
A17: Unlevered Free Cash Flow | B17: =B13+B14+B15+B16 -> -693.44054 | C17: =C13+C14+C15+C16 -> -533.4634 | D17: =D13+D14+D15+D16 -> -241.32064 | E17: =E13+E14+E15+E16 -> 294.47698 | F17: =F13+F14+F15+F16 -> 831.51459 | G17: =G13+G14+G15+G16 -> 852.30246
A19: Discount Period | B19: 1 | C19: 2 | D19: 3 | E19: 4 | F19: 5
A20: Discount Factor | B20: =1/(1+$B$26)^B19 -> 0.89847439 | C20: =1/(1+$B$26)^C19 -> 0.80725623 | D20: =1/(1+$B$26)^D19 -> 0.72529905 | E20: =1/(1+$B$26)^E19 -> 0.65166262 | F20: =1/(1+$B$26)^F19 -> 0.58550217
A21: PV of Unlevered FCF | B21: =B17*B20 -> -623.03857 | C21: =C17*C20 -> -430.64165 | D21: =D17*D20 -> -175.02963 | E21: =E17*E20 -> 191.89964 | F21: =F17*F20 -> 486.8536
A23: Valuation Summary
A24: Sum of PV of Explicit-Period FCF | B24: =SUM(B21:F21) -> -549.95661
A25: Terminal Growth Rate (g) | B25: =Assumptions!B14 -> 0.025
A26: WACC (from WACC tab) | B26: =WACC!B22 -> 0.11299778
A27: Terminal Value (Gordon Growth) | B27: =F17*(1+B25)/(B26-B25) -> 9685.4996
A28: PV of Terminal Value | B28: =B27/(1+B26)^F19 -> 5670.881
A29: Enterprise Value | B29: =B24+B28 -> 5120.9244
A30: Less: Total Debt | B30: =-'Debt Schedule'!B23 -> -2070
A31: Add: Cash & Equivalents | B31: ='Debt Schedule'!B25 -> 482.5
A32: Equity Value | B32: =B29+B30+B31 -> 3533.4244
A33: Diluted Shares Outstanding | B33: =WACC!B27 -> 400
A34: Implied Value per Share | B34: =B32/B33 -> 8.833561

Sheet Revenue & Cost Drivers
A1: VoltDrive Motors — Revenue & Cost Drivers Template
A2: Build volume, price, and unit-cost drivers here, then feed the results into the DCF tab.
B4: FY2025A | C4: FY2026E | D4: FY2027E | E4: FY2028E | F4: FY2029E | G4: FY2030E
A6: Revenue Drivers
A7: Vehicles Sold (units, '000) | B7: =B11/B9 -> 59.618442 | C7: =B7*(1+C8) -> 66.772655 | D7: =C7*(1+D8) -> 83.465819 | E7: =D7*(1+E8) -> 112.67886 | F7: =E7*(1+F8) -> 144.22893 | G7: =F7*(1+G8) -> 170.19014
A8: Unit Growth % | C8: =Assumptions!C17 -> 0.12 | D8: =Assumptions!D17 -> 0.25 | E8: =Assumptions!E17 -> 0.35 | F8: =Assumptions!F17 -> 0.28 | G8: =Assumptions!G17 -> 0.18
A9: Average Selling Price (ASP, $'000/unit) | B9: 74 | C9: =B9+(D9-B9)/2 -> 71 | D9: =Assumptions!D18 -> 68 | E9: =D9+($G$9-$D$9)/3 -> 63.666667 | F9: =E9+($G$9-$D$9)/3 -> 59.333333 | G9: =Assumptions!G18 -> 55
A10: ASP Growth % | C10: =C9/B9-1 -> -0.040540541 | D10: =D9/C9-1 -> -0.042253521 | E10: =E9/D9-1 -> -0.06372549 | F10: =F9/E9-1 -> -0.068062827 | G10: =G9/F9-1 -> -0.073033708
A11: Revenue from Vehicle Sales ($mm) | B11: ='Income Statement'!C6/(1+'Revenue & Cost Drivers'!B29) -> 4411.7647 | C11: =C7*C9 -> 4740.8585 | D11: =D7*D9 -> 5675.6757 | E11: =E7*E9 -> 7173.8871 | F11: =F7*F9 -> 8557.5835 | G11: =G7*G9 -> 9360.4579
A12: Other Revenue (services, software, energy) ($mm) | B12: =B11*B29 -> 88.235294 | C12: =C11*C29 -> 94.81717 | D12: =D11*D29 -> 113.51351 | E12: =E11*E29 -> 143.47774 | F12: =F11*F29 -> 171.15167 | G12: =G11*G29 -> 187.20916
A13: Total Revenue ($mm) | B13: =B11+B12 -> 4500 | C13: =C11+C12 -> 4835.6757 | D13: =D11+D12 -> 5789.1892 | E13: =E11+E12 -> 7317.3649 | F13: =F11+F12 -> 8728.7351 | G13: =G11+G12 -> 9547.667
A15: Cost Drivers
A16: Battery Cost per Unit ($'000) | B16: =Assumptions!B22 -> 21 | C16: =Assumptions!C22 -> 18.5 | D16: =Assumptions!D22 -> 15.8 | E16: =Assumptions!E22 -> 13.2 | F16: =Assumptions!F22 -> 11.5 | G16: =Assumptions!G22 -> 10.2
A17: Other Materials/Assembly Cost per Unit ($'000) | B17: =Assumptions!B23 -> 45 | C17: =Assumptions!C23 -> 42 | D17: =Assumptions!D23 -> 38.5 | E17: =Assumptions!E23 -> 34 | F17: =Assumptions!F23 -> 30.5 | G17: =Assumptions!G23 -> 28
A18: Total Variable Cost per Unit ($'000) | B18: =B16+B17 -> 66 | C18: =C16+C17 -> 60.5 | D18: =D16+D17 -> 54.3 | E18: =E16+E17 -> 47.2 | F18: =F16+F17 -> 42 | G18: =G16+G17 -> 38.2
A19: COGS ($mm) | B19: ='Income Statement'!C8 -> 3375 | C19: =C7*C18 -> 4039.7456 | D19: =D7*D18 -> 4532.194 | E19: =E7*E18 -> 5318.442 | F19: =F7*F18 -> 6057.6153 | G19: =G7*G18 -> 6501.2635
A20: Gross Margin % | B20: =(B13-B19)/B13 -> 0.25 | C20: =(C13-C19)/C13 -> 0.16459542 | D20: =(D13-D19)/D13 -> 0.21712803 | E20: =(E13-E19)/E13 -> 0.27317524 | F20: =(F13-F19)/F13 -> 0.30601454 | G20: =(G13-G19)/G13 -> 0.31907308
A21: R&D as % of Revenue | B21: ='Income Statement'!C10/'Revenue & Cost Drivers'!B13 -> 0.08 | C21: =Assumptions!C26 -> 0.14 | D21: =Assumptions!D26 -> 0.115 | E21: =Assumptions!E26 -> 0.09 | F21: =Assumptions!F26 -> 0.075 | G21: =Assumptions!G26 -> 0.065
A22: R&D Expense ($mm) | B22: ='Income Statement'!C10 -> 360 | C22: =C13*C21 -> 676.99459 | D22: =D13*D21 -> 665.75676 | E22: =E13*E21 -> 658.56284 | F22: =F13*F21 -> 654.65514 | G22: =G13*G21 -> 620.59836
A23: SG&A as % of Revenue | B23: ='Income Statement'!C11/'Revenue & Cost Drivers'!B13 -> 0.1 | C23: =Assumptions!C27 -> 0.15 | D23: =Assumptions!D27 -> 0.125 | E23: =Assumptions!E27 -> 0.105 | F23: =Assumptions!F27 -> 0.09 | G23: =Assumptions!G27 -> 0.08
A24: SG&A Expense ($mm) | B24: ='Income Statement'!C11 -> 450 | C24: =C13*C23 -> 725.35135 | D24: =D13*D23 -> 723.64865 | E24: =E13*E23 -> 768.32331 | F24: =F13*F23 -> 785.58616 | G24: =G13*G23 -> 763.81336
A28: Additional Assumptions & Reconciliation (added)
A29: Other Revenue as % of Vehicle Sales Revenue | B29: =Assumptions!$B$19 -> 0.02 | C29: =Assumptions!$B$19 -> 0.02 | D29: =Assumptions!$B$19 -> 0.02 | E29: =Assumptions!$B$19 -> 0.02 | F29: =Assumptions!$B$19 -> 0.02 | G29: =Assumptions!$B$19 -> 0.02
A30: FY25A implied units back-solved: (Reported Revenue / (1 + Other %)) / ASP
A31: FY25A COGS implied by unit-cost drivers ($mm) = Units x $66.0k | B31: =B7*B18 -> 3934.8172
A32: FY25A variance: driver-implied COGS less reported COGS ($mm) | B32: =B31-B19 -> 559.81717

Sheet Capacity Expansion
A1: VoltDrive Motors — Capacity Expansion Template
A2: Link required capacity to unit sales from the Revenue & Cost Drivers tab, then size capex to close any capacity gap.
B4: FY2025A | C4: FY2026E | D4: FY2027E | E4: FY2028E | F4: FY2029E | G4: FY2030E
A6: Demand Side
A7: Required Units Sold (from Drivers tab, '000) | B7: ='Revenue & Cost Drivers'!B7 -> 59.618442 | C7: ='Revenue & Cost Drivers'!C7 -> 66.772655 | D7: ='Revenue & Cost Drivers'!D7 -> 83.465819 | E7: ='Revenue & Cost Drivers'!E7 -> 112.67886 | F7: ='Revenue & Cost Drivers'!F7 -> 144.22893 | G7: ='Revenue & Cost Drivers'!G7 -> 170.19014
A8: Required Annual Capacity (units, '000) | B8: =B7/B9 -> 100 | C8: =C7/C9 -> 102.72716 | D8: =D7/D9 -> 117.14501 | E8: =E7/E9 -> 145.39207 | F8: =F7/F9 -> 172.21365 | G8: =G7/G9 -> 189.10016
A9: Utilization Target % | B9: =B7/B15 -> 0.59618442 | C9: =Assumptions!C31 -> 0.65 | D9: =C9+($G$9-$C$9)/4 -> 0.7125 | E9: =D9+($G$9-$C$9)/4 -> 0.775 | F9: =E9+($G$9-$C$9)/4 -> 0.8375 | G9: =Assumptions!G31 -> 0.9
A11: Supply Side
A12: Existing Installed Capacity, Beginning (units, '000) | C12: =B15 -> 100 | D12: =C15 -> 102.72716 | E12: =D15 -> 117.14501 | F12: =E15 -> 145.39207 | G12: =F15 -> 172.21365
A13: Capacity Gap (Required – Existing) | C13: =MAX(0,C8-C12) -> 2.7271616 | D13: =MAX(0,D8-D12) -> 14.417847 | E13: =MAX(0,E8-E12) -> 28.247063 | F13: =MAX(0,F8-F12) -> 26.821582 | G13: =MAX(0,G8-G12) -> 16.886505
A14: New Capacity to be Added (units, '000) | C14: =C13 -> 2.7271616 | D14: =D13 -> 14.417847 | E14: =E13 -> 28.247063 | F14: =F13 -> 26.821582 | G14: =G13 -> 16.886505
A15: Installed Capacity, Ending (units, '000) | B15: =Assumptions!$B$30 -> 100 | C15: =C12+C14 -> 102.72716 | D15: =D12+D14 -> 117.14501 | E15: =E12+E14 -> 145.39207 | F15: =F12+F14 -> 172.21365 | G15: =G12+G14 -> 189.10016
A17: Capex Sizing
A18: Capex per Unit of New Capacity ($mm per '000 units) | C18: =Assumptions!$B$32 -> 12 | D18: =Assumptions!$B$32 -> 12 | E18: =Assumptions!$B$32 -> 12 | F18: =Assumptions!$B$32 -> 12 | G18: =Assumptions!$B$32 -> 12
A19: Growth / Expansion Capex ($mm) | C19: =C14*C18 -> 32.725939 | D19: =D14*D18 -> 173.01417 | E19: =E14*E18 -> 338.96475 | F19: =F14*F18 -> 321.85899 | G19: =G14*G18 -> 202.63807
A20: Maintenance Capex ($mm) | C20: ='Revenue & Cost Drivers'!C13*C31 -> 169.24865 | D20: ='Revenue & Cost Drivers'!D13*D31 -> 188.14865 | E20: ='Revenue & Cost Drivers'!E13*E31 -> 219.52095 | F20: ='Revenue & Cost Drivers'!F13*F31 -> 240.04022 | G20: ='Revenue & Cost Drivers'!G13*G31 -> 238.69168
A21: Total Capex ($mm) | B21: =-'Cash Flow Statement'!C14 -> 560 | C21: =C19+C20 -> 201.97459 | D21: =D19+D20 -> 361.16282 | E21: =E19+E20 -> 558.4857 | F21: =F19+F20 -> 561.8992 | G21: =G19+G20 -> 441.32974
A23: PP&E Roll-forward
A24: Net PP&E, Beginning ($mm) | B24: ='Balance Sheet'!B10 -> 2625 | C24: =B27 -> 2985 | D24: =C27 -> 2959.546 | E24: =D27 -> 3095.2196 | F24: =E27 -> 3417.8791 | G24: =F27 -> 3719.3684
A25: Add: Total Capex ($mm) | B25: =B21 -> 560 | C25: =C21 -> 201.97459 | D25: =D21 -> 361.16282 | E25: =E21 -> 558.4857 | F25: =F21 -> 561.8992 | G25: =G21 -> 441.32974
A26: Less: D&A ($mm) | B26: ='Income Statement'!C13 -> 200 | C26: =C24*C32 -> 227.42857 | D26: =D24*D32 -> 225.48922 | E26: =E24*E32 -> 235.82626 | F26: =F24*F32 -> 260.40983 | G26: =G24*G32 -> 283.38045
A27: Net PP&E, Ending ($mm) | B27: =B24+B25-B26 -> 2985 | C27: =C24+C25-C26 -> 2959.546 | D27: =D24+D25-D26 -> 3095.2196 | E27: =E24+E25-E26 -> 3417.8791 | F27: =F24+F25-F26 -> 3719.3684 | G27: =G24+G25-G26 -> 3877.3177
A28: Additional Assumptions & Reconciliation (added)
A29: Other Revenue as % of Vehicle Sales Revenue
A30: FY25A implied units back-solved: (Reported Revenue / (1 + Other %)) / ASP
A31: FY25A COGS implied by unit-cost drivers ($mm) = Units x $66.0k | C31: =Assumptions!C33 -> 0.035 | D31: =C31+($G$31-$C$31)/4 -> 0.0325 | E31: =D31+($G$31-$C$31)/4 -> 0.03 | F31: =E31+($G$31-$C$31)/4 -> 0.0275 | G31: =Assumptions!G33 -> 0.025
A32: FY25A variance: driver-implied COGS less reported COGS ($mm) | B32: ='Income Statement'!C13/'Balance Sheet'!B10 -> 0.076190476 | C32: =B32 -> 0.076190476 | D32: =C32 -> 0.076190476 | E32: =D32 -> 0.076190476 | F32: =E32 -> 0.076190476 | G32: =F32 -> 0.076190476

Sheet Debt Schedule
A1: VoltDrive Motors — Debt Schedule Template
A2: Build opening/closing balances, draws, and interest for each tranche; link interest expense back to the Income Statement.
B4: FY2025A | C4: FY2026E | D4: FY2027E | E4: FY2028E | F4: FY2029E | G4: FY2030E
A6: Short-Term Debt / Revolver
A7: Beginning Balance | B7: ='Balance Sheet'!B15 -> 190 | C7: =B10 -> 190 | D7: =C10 -> 190 | E7: =D10 -> 190 | F7: =E10 -> 190 | G7: =F10 -> 190
A8: Draws | C8: =Assumptions!$B$36 -> 0 | D8: =Assumptions!$B$36 -> 0 | E8: =Assumptions!$B$36 -> 0 | F8: =Assumptions!$B$36 -> 0 | G8: =Assumptions!$B$36 -> 0
A9: Repayments | C9: =Assumptions!$B$37 -> 0 | D9: =Assumptions!$B$37 -> 0 | E9: =Assumptions!$B$37 -> 0 | F9: =Assumptions!$B$37 -> 0 | G9: =Assumptions!$B$37 -> 0
A10: Ending Balance | B10: ='Balance Sheet'!C15 -> 190 | C10: =C7+C8+C9 -> 190 | D10: =D7+D8+D9 -> 190 | E10: =E7+E8+E9 -> 190 | F10: =F7+F8+F9 -> 190 | G10: =G7+G8+G9 -> 190
A11: Interest Rate % | C11: =WACC!$B$11 -> 0.075 | D11: =WACC!$B$11 -> 0.075 | E11: =WACC!$B$11 -> 0.075 | F11: =WACC!$B$11 -> 0.075 | G11: =WACC!$B$11 -> 0.075
A12: Interest Expense | C12: =C7*C11 -> 14.25 | D12: =D7*D11 -> 14.25 | E12: =E7*E11 -> 14.25 | F12: =F7*F11 -> 14.25 | G12: =G7*G11 -> 14.25
A14: Long-Term Debt / Term Loan
A15: Beginning Balance | B15: ='Balance Sheet'!B17 -> 1700 | C15: =B18 -> 1880 | D15: =C18 -> 1886.9873 | E15: =D18 -> 1973.2193 | F15: =E18 -> 2153.8012 | G15: =F18 -> 2327.0608
A16: New Issuance (funds capex/expansion) | B16: ='Cash Flow Statement'!C18 -> 280 | C16: =C30*'Capacity Expansion'!C21 -> 100.98729 | D16: =D30*'Capacity Expansion'!D21 -> 180.58141 | E16: =E30*'Capacity Expansion'!E21 -> 279.24285 | F16: =F30*'Capacity Expansion'!F21 -> 280.9496 | G16: =G30*'Capacity Expansion'!G21 -> 220.66487
A17: Scheduled Repayments | B17: ='Cash Flow Statement'!C19 -> -100 | C17: =-C31*C15 -> -94 | D17: =-D31*D15 -> -94.349365 | E17: =-E31*E15 -> -98.660967 | F17: =-F31*F15 -> -107.69006 | G17: =-G31*G15 -> -116.35304
A18: Ending Balance | B18: =B15+B16+B17 -> 1880 | C18: =C15+C16+C17 -> 1886.9873 | D18: =D15+D16+D17 -> 1973.2193 | E18: =E15+E16+E17 -> 2153.8012 | F18: =F15+F16+F17 -> 2327.0608 | G18: =G15+G16+G17 -> 2431.3726
A19: Interest Rate % | C19: =WACC!$B$11 -> 0.075 | D19: =WACC!$B$11 -> 0.075 | E19: =WACC!$B$11 -> 0.075 | F19: =WACC!$B$11 -> 0.075 | G19: =WACC!$B$11 -> 0.075
A20: Interest Expense | C20: =C15*C19 -> 141 | D20: =D15*D19 -> 141.52405 | E20: =E15*E19 -> 147.99145 | F20: =F15*F19 -> 161.53509 | G20: =G15*G19 -> 174.52956
A22: Total Debt Summary
A23: Total Debt, Ending Balance | B23: =B10+B18 -> 2070 | C23: =C10+C18 -> 2076.9873 | D23: =D10+D18 -> 2163.2193 | E23: =E10+E18 -> 2343.8012 | F23: =F10+F18 -> 2517.0608 | G23: =G10+G18 -> 2621.3726
A24: Total Interest Expense | B24: ='Income Statement'!C15 -> 85 | C24: =C12+C20 -> 155.25 | D24: =D12+D20 -> 155.77405 | E24: =E12+E20 -> 162.24145 | F24: =F12+F20 -> 175.78509 | G24: =G12+G20 -> 188.77956
A25: Cash Balance (min cash / sweep check) | B25: ='Balance Sheet'!C6 -> 482.5 | C25: ='Balance Sheet'!D6 -> 400 | D25: ='Balance Sheet'!E6 -> 400 | E25: ='Balance Sheet'!F6 -> 400 | F25: ='Balance Sheet'!G6 -> 728.8663 | G25: ='Balance Sheet'!H6 -> 1515.5569
A29: Additional Assumptions (added)
A30: New LT Debt as % of Total Capex | C30: =Assumptions!$B$38 -> 0.5 | D30: =Assumptions!$B$38 -> 0.5 | E30: =Assumptions!$B$38 -> 0.5 | F30: =Assumptions!$B$38 -> 0.5 | G30: =Assumptions!$B$38 -> 0.5
A31: Scheduled LT Repayment (% of Beginning LT Balance) | C31: =Assumptions!$B$39 -> 0.05 | D31: =Assumptions!$B$39 -> 0.05 | E31: =Assumptions!$B$39 -> 0.05 | F31: =Assumptions!$B$39 -> 0.05 | G31: =Assumptions!$B$39 -> 0.05
A32: Minimum Cash Balance ($mm) - shortfall funded by equity issuance (CFS row 20) | C32: =Assumptions!$B$40 -> 400 | D32: =Assumptions!$B$40 -> 400 | E32: =Assumptions!$B$40 -> 400 | F32: =Assumptions!$B$40 -> 400 | G32: =Assumptions!$B$40 -> 400
